clt_py/__init__.py
clt_py/clt_py.py
clt_py-0.0.4.dist-info/AUTHORS.rst
clt_py-0.0.4.dist-info/LICENSE
clt_py-0.0.4.dist-info/METADATA
clt_py-0.0.4.dist-info/WHEEL
clt_py-0.0.4.dist-info/top_level.txt
clt_py-0.0.4.dist-info/RECORD
