Metadata-Version: 2.1
Name: clt-py
Version: 0.0.4
Summary: This packages provides methodes for calculating fiber-reinforced materials.
Home-page: https://github.com/axelschmidt91/clt_py
Author: Axel Schmidt
Author-email: schmidt.axel.91@gmail.com
License: MIT license
Keywords: clt_py
Platform: UNKNOWN
Classifier: Development Status :: 2 - Pre-Alpha
Classifier: Intended Audience :: Developers
Classifier: License :: OSI Approved :: MIT License
Classifier: Natural Language :: English
Classifier: Programming Language :: Python :: 3
Classifier: Programming Language :: Python :: 3.6
Classifier: Programming Language :: Python :: 3.7
Classifier: Programming Language :: Python :: 3.8
Requires-Python: >=3.6
Requires-Dist: numpy (==1.18.1)
